{"name":"Successfully update a book\u0027s details","id":"books-api-crud-operations;successfully-update-a-book-s-details","scenarioId":"BooksAPIOperations:Successfully update a book\u0027s details","methodName":"Successfully update a book\u0027s details","testSteps":[{"number":1,"description":"1: Successfully update a book\u0027s details ({TestCaseName\u003dUpdateBookDetails_NameUpdate, FieldName\u003dname})","duration":4101,"startTime":"2025-03-27T00:47:53.177065+05:30[Asia/Kolkata]","result":"SUCCESS","precondition":false,"level":0,"lineNumber":76,"children":[{"number":2,"description":"Given A book already exists for test - \"UpdateBookDetails_NameUpdate\"","duration":1355,"startTime":"2025-03-27T00:47:53.178398+05:30[Asia/Kolkata]","result":"SUCCESS","precondition":false,"level":1,"children":[{"number":3,"description":"POST http://77.102.250.113:17354/api/v1/books","duration":0,"startTime":"2025-03-27T00:47:54.515622+05:30[Asia/Kolkata]","result":"SUCCESS","restQuery":{"method":"POST","path":"http://77.102.250.113:17354/api/v1/books","content":"{\n    \"id\": 0,\n    \"name\": \"The Lord of the Rings by J.R.R. Tolkien\",\n    \"author\": \"J.R.R. Tolkien\",\n    \"publication\": \"Macmillan Publishers\",\n    \"category\": \"Science\",\n    \"pages\": \"200\",\n    \"price\": \"500\"\n}","contentType":"application/json","requestHeaders":"Accept\u003d*/*\n\t\t\t\tContent-Type\u003dapplication/json","requestCookies":"","responseHeaders":"Set-Cookie: JSESSIONID\u003dD20A5884531EF9C525001C904B868B37; Path\u003d/; HttpOnly\nX-Content-Type-Options: nosniff\nX-XSS-Protection: 1; mode\u003dblock\nCache-Control: no-cache, no-store, max-age\u003d0, must-revalidate\nPragma: no-cache\nExpires: 0\nX-Frame-Options: DENY\nContent-Type: application/json\nTransfer-Encoding: chunked\nDate: Wed, 26 Mar 2025 19:17:53 GMT\nKeep-Alive: timeout\u003d60\nConnection: keep-alive","responseCookies":"JSESSIONID\u003dD20A5884531EF9C525001C904B868B37;Path\u003d/;HttpOnly","responseBody":"{\n    \"id\": 7396,\n    \"name\": \"The Lord of the Rings by J.R.R. Tolkien\",\n    \"author\": \"J.R.R. Tolkien\",\n    \"publication\": \"Macmillan Publishers\",\n    \"category\": \"Science\",\n    \"pages\": 200,\n    \"price\": 500.0\n}","statusCode":200},"precondition":false,"level":2}]},{"number":4,"description":"When User updates the book details for field - \"name\"","duration":1432,"startTime":"2025-03-27T00:47:54.534392+05:30[Asia/Kolkata]","result":"SUCCESS","precondition":false,"level":1,"children":[{"number":5,"description":"PUT http://77.102.250.113:17354/api/v1/books/7396","duration":0,"startTime":"2025-03-27T00:47:55.963651+05:30[Asia/Kolkata]","result":"SUCCESS","restQuery":{"method":"PUT","path":"http://77.102.250.113:17354/api/v1/books/7396","content":"{\n    \"id\": 7396,\n    \"name\": \"Updated Name\",\n    \"author\": \"J.R.R. Tolkien\",\n    \"publication\": \"Macmillan Publishers\",\n    \"category\": \"Science\",\n    \"pages\": \"200\",\n    \"price\": \"500\"\n}","contentType":"application/json","requestHeaders":"Accept\u003d*/*\n\t\t\t\tContent-Type\u003dapplication/json","requestCookies":"","responseHeaders":"Set-Cookie: JSESSIONID\u003d76A50F4A3D51B10B048D0D832DF6BA2C; Path\u003d/; HttpOnly\nX-Content-Type-Options: nosniff\nX-XSS-Protection: 1; mode\u003dblock\nCache-Control: no-cache, no-store, max-age\u003d0, must-revalidate\nPragma: no-cache\nExpires: 0\nX-Frame-Options: DENY\nContent-Type: application/json\nTransfer-Encoding: chunked\nDate: Wed, 26 Mar 2025 19:17:55 GMT\nKeep-Alive: timeout\u003d60\nConnection: keep-alive","responseCookies":"JSESSIONID\u003d76A50F4A3D51B10B048D0D832DF6BA2C;Path\u003d/;HttpOnly","responseBody":"{\n    \"id\": 7396,\n    \"name\": \"Updated Name\",\n    \"author\": \"J.R.R. Tolkien\",\n    \"publication\": \"Macmillan Publishers\",\n    \"category\": \"Science\",\n    \"pages\": 200,\n    \"price\": 500.0\n}","statusCode":200},"precondition":false,"level":2}]},{"number":6,"description":"Then The book details should be updated successfully","duration":1308,"startTime":"2025-03-27T00:47:55.968458+05:30[Asia/Kolkata]","result":"SUCCESS","precondition":false,"level":1,"children":[{"number":7,"description":"GET http://77.102.250.113:17354/api/v1/books/7396","duration":0,"startTime":"2025-03-27T00:47:57.268042+05:30[Asia/Kolkata]","result":"SUCCESS","restQuery":{"method":"GET","path":"http://77.102.250.113:17354/api/v1/books/7396","content":"","contentType":"null","requestHeaders":"Accept\u003d*/*","requestCookies":"","responseHeaders":"Set-Cookie: JSESSIONID\u003d5C61D05DE382A0182B6773BCA12D7760; Path\u003d/; HttpOnly\nX-Content-Type-Options: nosniff\nX-XSS-Protection: 1; mode\u003dblock\nCache-Control: no-cache, no-store, max-age\u003d0, must-revalidate\nPragma: no-cache\nExpires: 0\nX-Frame-Options: DENY\nContent-Type: application/json\nTransfer-Encoding: chunked\nDate: Wed, 26 Mar 2025 19:17:56 GMT\nKeep-Alive: timeout\u003d60\nConnection: keep-alive","responseCookies":"JSESSIONID\u003d5C61D05DE382A0182B6773BCA12D7760;Path\u003d/;HttpOnly","responseBody":"{\n    \"id\": 7396,\n    \"name\": \"Updated Name\",\n    \"author\": \"J.R.R. Tolkien\",\n    \"publication\": \"Macmillan Publishers\",\n    \"category\": \"Science\",\n    \"pages\": 200,\n    \"price\": 500.0\n}","statusCode":200},"precondition":false,"level":2}]}]},{"number":8,"description":"2: Successfully update a book\u0027s details ({TestCaseName\u003dUpdateBookDetails_AuthorUpdate, FieldName\u003dauthor})","duration":4183,"startTime":"2025-03-27T00:47:57.296011+05:30[Asia/Kolkata]","result":"SUCCESS","precondition":false,"level":0,"lineNumber":77,"children":[{"number":9,"description":"Given A book already exists for test - \"UpdateBookDetails_AuthorUpdate\"","duration":1415,"startTime":"2025-03-27T00:47:57.297530+05:30[Asia/Kolkata]","result":"SUCCESS","precondition":false,"level":1,"children":[{"number":10,"description":"POST http://77.102.250.113:17354/api/v1/books","duration":0,"startTime":"2025-03-27T00:47:58.695034+05:30[Asia/Kolkata]","result":"SUCCESS","restQuery":{"method":"POST","path":"http://77.102.250.113:17354/api/v1/books","content":"{\n    \"id\": 0,\n    \"name\": \"The Harry Potter Series by J.K. Rowling\",\n    \"author\": \"J.K. Rowling\",\n    \"publication\": \"Hachette Book Group\",\n    \"category\": \"History\",\n    \"pages\": \"203\",\n    \"price\": \"2330\"\n}","contentType":"application/json","requestHeaders":"Accept\u003d*/*\n\t\t\t\tContent-Type\u003dapplication/json","requestCookies":"","responseHeaders":"Set-Cookie: JSESSIONID\u003dA0A40FF602DF845B6FE3018F8A8826B1; Path\u003d/; HttpOnly\nX-Content-Type-Options: nosniff\nX-XSS-Protection: 1; mode\u003dblock\nCache-Control: no-cache, no-store, max-age\u003d0, must-revalidate\nPragma: no-cache\nExpires: 0\nX-Frame-Options: DENY\nContent-Type: application/json\nTransfer-Encoding: chunked\nDate: Wed, 26 Mar 2025 19:17:57 GMT\nKeep-Alive: timeout\u003d60\nConnection: keep-alive","responseCookies":"JSESSIONID\u003dA0A40FF602DF845B6FE3018F8A8826B1;Path\u003d/;HttpOnly","responseBody":"{\n    \"id\": 7397,\n    \"name\": \"The Harry Potter Series by J.K. Rowling\",\n    \"author\": \"J.K. Rowling\",\n    \"publication\": \"Hachette Book Group\",\n    \"category\": \"History\",\n    \"pages\": 203,\n    \"price\": 2330.0\n}","statusCode":200},"precondition":false,"level":2}]},{"number":11,"description":"When User updates the book details for field - \"author\"","duration":1345,"startTime":"2025-03-27T00:47:58.714384+05:30[Asia/Kolkata]","result":"SUCCESS","precondition":false,"level":1,"children":[{"number":12,"description":"PUT http://77.102.250.113:17354/api/v1/books/7397","duration":0,"startTime":"2025-03-27T00:48:00.057611+05:30[Asia/Kolkata]","result":"SUCCESS","restQuery":{"method":"PUT","path":"http://77.102.250.113:17354/api/v1/books/7397","content":"{\n    \"id\": 7397,\n    \"name\": \"The Harry Potter Series by J.K. Rowling\",\n    \"author\": \"Updated Author\",\n    \"publication\": \"Hachette Book Group\",\n    \"category\": \"History\",\n    \"pages\": \"203\",\n    \"price\": \"2330\"\n}","contentType":"application/json","requestHeaders":"Accept\u003d*/*\n\t\t\t\tContent-Type\u003dapplication/json","requestCookies":"","responseHeaders":"Set-Cookie: JSESSIONID\u003d68FC6AA9F9486D2AB2656CA846328C97; Path\u003d/; HttpOnly\nX-Content-Type-Options: nosniff\nX-XSS-Protection: 1; mode\u003dblock\nCache-Control: no-cache, no-store, max-age\u003d0, must-revalidate\nPragma: no-cache\nExpires: 0\nX-Frame-Options: DENY\nContent-Type: application/json\nTransfer-Encoding: chunked\nDate: Wed, 26 Mar 2025 19:17:59 GMT\nKeep-Alive: timeout\u003d60\nConnection: keep-alive","responseCookies":"JSESSIONID\u003d68FC6AA9F9486D2AB2656CA846328C97;Path\u003d/;HttpOnly","responseBody":"{\n    \"id\": 7397,\n    \"name\": \"The Harry Potter Series by J.K. Rowling\",\n    \"author\": \"Updated Author\",\n    \"publication\": \"Hachette Book Group\",\n    \"category\": \"History\",\n    \"pages\": 203,\n    \"price\": 2330.0\n}","statusCode":200},"precondition":false,"level":2}]},{"number":13,"description":"Then The book details should be updated successfully","duration":1416,"startTime":"2025-03-27T00:48:00.061092+05:30[Asia/Kolkata]","result":"SUCCESS","precondition":false,"level":1,"children":[{"number":14,"description":"GET http://77.102.250.113:17354/api/v1/books/7397","duration":0,"startTime":"2025-03-27T00:48:01.471033+05:30[Asia/Kolkata]","result":"SUCCESS","restQuery":{"method":"GET","path":"http://77.102.250.113:17354/api/v1/books/7397","content":"","contentType":"null","requestHeaders":"Accept\u003d*/*","requestCookies":"","responseHeaders":"Set-Cookie: JSESSIONID\u003d383438ADE35665BA4B2AA77A8A4C678C; Path\u003d/; HttpOnly\nX-Content-Type-Options: nosniff\nX-XSS-Protection: 1; mode\u003dblock\nCache-Control: no-cache, no-store, max-age\u003d0, must-revalidate\nPragma: no-cache\nExpires: 0\nX-Frame-Options: DENY\nContent-Type: application/json\nTransfer-Encoding: chunked\nDate: Wed, 26 Mar 2025 19:18:00 GMT\nKeep-Alive: timeout\u003d60\nConnection: keep-alive","responseCookies":"JSESSIONID\u003d383438ADE35665BA4B2AA77A8A4C678C;Path\u003d/;HttpOnly","responseBody":"{\n    \"id\": 7397,\n    \"name\": \"The Harry Potter Series by J.K. Rowling\",\n    \"author\": \"Updated Author\",\n    \"publication\": \"Hachette Book Group\",\n    \"category\": \"History\",\n    \"pages\": 203,\n    \"price\": 2330.0\n}","statusCode":200},"precondition":false,"level":2}]}]},{"number":15,"description":"3: Successfully update a book\u0027s details ({TestCaseName\u003dUpdateBookDetails_PublicationUpdate, FieldName\u003dpublication})","duration":4285,"startTime":"2025-03-27T00:48:01.498976+05:30[Asia/Kolkata]","result":"SUCCESS","precondition":false,"level":0,"lineNumber":78,"children":[{"number":16,"description":"Given A book already exists for test - \"UpdateBookDetails_PublicationUpdate\"","duration":1416,"startTime":"2025-03-27T00:48:01.499536+05:30[Asia/Kolkata]","result":"SUCCESS","precondition":false,"level":1,"children":[{"number":17,"description":"POST http://77.102.250.113:17354/api/v1/books","duration":0,"startTime":"2025-03-27T00:48:02.891938+05:30[Asia/Kolkata]","result":"SUCCESS","restQuery":{"method":"POST","path":"http://77.102.250.113:17354/api/v1/books","content":"{\n    \"id\": 0,\n    \"name\": \"The Alchemist by Paulo Coelho\",\n    \"author\": \"Paulo Coelho\",\n    \"publication\": \"Bloomsbury Publishing\",\n    \"category\": \"Programming\",\n    \"pages\": \"345\",\n    \"price\": \"600\"\n}","contentType":"application/json","requestHeaders":"Accept\u003d*/*\n\t\t\t\tContent-Type\u003dapplication/json","requestCookies":"","responseHeaders":"Set-Cookie: JSESSIONID\u003d72F99EDB5104D15F8569D3278096347D; Path\u003d/; HttpOnly\nX-Content-Type-Options: nosniff\nX-XSS-Protection: 1; mode\u003dblock\nCache-Control: no-cache, no-store, max-age\u003d0, must-revalidate\nPragma: no-cache\nExpires: 0\nX-Frame-Options: DENY\nContent-Type: application/json\nTransfer-Encoding: chunked\nDate: Wed, 26 Mar 2025 19:18:02 GMT\nKeep-Alive: timeout\u003d60\nConnection: keep-alive","responseCookies":"JSESSIONID\u003d72F99EDB5104D15F8569D3278096347D;Path\u003d/;HttpOnly","responseBody":"{\n    \"id\": 7398,\n    \"name\": \"The Alchemist by Paulo Coelho\",\n    \"author\": \"Paulo Coelho\",\n    \"publication\": \"Bloomsbury Publishing\",\n    \"category\": \"Programming\",\n    \"pages\": 345,\n    \"price\": 600.0\n}","statusCode":200},"precondition":false,"level":2}]},{"number":18,"description":"When User updates the book details for field - \"publication\"","duration":1515,"startTime":"2025-03-27T00:48:02.916693+05:30[Asia/Kolkata]","result":"SUCCESS","precondition":false,"level":1,"children":[{"number":19,"description":"PUT http://77.102.250.113:17354/api/v1/books/7398","duration":0,"startTime":"2025-03-27T00:48:04.428983+05:30[Asia/Kolkata]","result":"SUCCESS","restQuery":{"method":"PUT","path":"http://77.102.250.113:17354/api/v1/books/7398","content":"{\n    \"id\": 7398,\n    \"name\": \"The Alchemist by Paulo Coelho\",\n    \"author\": \"Paulo Coelho\",\n    \"publication\": \"Updated Publication\",\n    \"category\": \"Programming\",\n    \"pages\": \"345\",\n    \"price\": \"600\"\n}","contentType":"application/json","requestHeaders":"Accept\u003d*/*\n\t\t\t\tContent-Type\u003dapplication/json","requestCookies":"","responseHeaders":"Set-Cookie: JSESSIONID\u003d22F4CA2805183B0E2582D195D3A1A67B; Path\u003d/; HttpOnly\nX-Content-Type-Options: nosniff\nX-XSS-Protection: 1; mode\u003dblock\nCache-Control: no-cache, no-store, max-age\u003d0, must-revalidate\nPragma: no-cache\nExpires: 0\nX-Frame-Options: DENY\nContent-Type: application/json\nTransfer-Encoding: chunked\nDate: Wed, 26 Mar 2025 19:18:03 GMT\nKeep-Alive: timeout\u003d60\nConnection: keep-alive","responseCookies":"JSESSIONID\u003d22F4CA2805183B0E2582D195D3A1A67B;Path\u003d/;HttpOnly","responseBody":"{\n    \"id\": 7398,\n    \"name\": \"The Alchemist by Paulo Coelho\",\n    \"author\": \"Paulo Coelho\",\n    \"publication\": \"Updated Publication\",\n    \"category\": \"Programming\",\n    \"pages\": 345,\n    \"price\": 600.0\n}","statusCode":200},"precondition":false,"level":2}]},{"number":20,"description":"Then The book details should be updated successfully","duration":1350,"startTime":"2025-03-27T00:48:04.432857+05:30[Asia/Kolkata]","result":"SUCCESS","precondition":false,"level":1,"children":[{"number":21,"description":"GET http://77.102.250.113:17354/api/v1/books/7398","duration":0,"startTime":"2025-03-27T00:48:05.777947+05:30[Asia/Kolkata]","result":"SUCCESS","restQuery":{"method":"GET","path":"http://77.102.250.113:17354/api/v1/books/7398","content":"","contentType":"null","requestHeaders":"Accept\u003d*/*","requestCookies":"","responseHeaders":"Set-Cookie: JSESSIONID\u003d398DD0A2822D82FA8E05A7EC01799871; Path\u003d/; HttpOnly\nX-Content-Type-Options: nosniff\nX-XSS-Protection: 1; mode\u003dblock\nCache-Control: no-cache, no-store, max-age\u003d0, must-revalidate\nPragma: no-cache\nExpires: 0\nX-Frame-Options: DENY\nContent-Type: application/json\nTransfer-Encoding: chunked\nDate: Wed, 26 Mar 2025 19:18:04 GMT\nKeep-Alive: timeout\u003d60\nConnection: keep-alive","responseCookies":"JSESSIONID\u003d398DD0A2822D82FA8E05A7EC01799871;Path\u003d/;HttpOnly","responseBody":"{\n    \"id\": 7398,\n    \"name\": \"The Alchemist by Paulo Coelho\",\n    \"author\": \"Paulo Coelho\",\n    \"publication\": \"Updated Publication\",\n    \"category\": \"Programming\",\n    \"pages\": 345,\n    \"price\": 600.0\n}","statusCode":200},"precondition":false,"level":2}]}]},{"number":22,"description":"4: Successfully update a book\u0027s details ({TestCaseName\u003dUpdateBookDetails_CategoryUpdate, FieldName\u003dcategory})","duration":4175,"startTime":"2025-03-27T00:48:05.795623+05:30[Asia/Kolkata]","result":"SUCCESS","precondition":false,"level":0,"lineNumber":79,"children":[{"number":23,"description":"Given A book already exists for test - \"UpdateBookDetails_CategoryUpdate\"","duration":1364,"startTime":"2025-03-27T00:48:05.796500+05:30[Asia/Kolkata]","result":"SUCCESS","precondition":false,"level":1,"children":[{"number":24,"description":"POST http://77.102.250.113:17354/api/v1/books","duration":0,"startTime":"2025-03-27T00:48:07.143934+05:30[Asia/Kolkata]","result":"SUCCESS","restQuery":{"method":"POST","path":"http://77.102.250.113:17354/api/v1/books","content":"{\n    \"id\": 0,\n    \"name\": \"The Da Vinci Code by Dan Brown\",\n    \"author\": \"Dan Brown\",\n    \"publication\": \"Penguin Books\",\n    \"category\": \"Web\",\n    \"pages\": \"500\",\n    \"price\": \"800\"\n}","contentType":"application/json","requestHeaders":"Accept\u003d*/*\n\t\t\t\tContent-Type\u003dapplication/json","requestCookies":"","responseHeaders":"Set-Cookie: JSESSIONID\u003d12361B18CB6F9A52C641CEF522EF28A2; Path\u003d/; HttpOnly\nX-Content-Type-Options: nosniff\nX-XSS-Protection: 1; mode\u003dblock\nCache-Control: no-cache, no-store, max-age\u003d0, must-revalidate\nPragma: no-cache\nExpires: 0\nX-Frame-Options: DENY\nContent-Type: application/json\nTransfer-Encoding: chunked\nDate: Wed, 26 Mar 2025 19:18:06 GMT\nKeep-Alive: timeout\u003d60\nConnection: keep-alive","responseCookies":"JSESSIONID\u003d12361B18CB6F9A52C641CEF522EF28A2;Path\u003d/;HttpOnly","responseBody":"{\n    \"id\": 7399,\n    \"name\": \"The Da Vinci Code by Dan Brown\",\n    \"author\": \"Dan Brown\",\n    \"publication\": \"Penguin Books\",\n    \"category\": \"Web\",\n    \"pages\": 500,\n    \"price\": 800.0\n}","statusCode":200},"precondition":false,"level":2}]},{"number":25,"description":"When User updates the book details for field - \"category\"","duration":1470,"startTime":"2025-03-27T00:48:07.162068+05:30[Asia/Kolkata]","result":"SUCCESS","precondition":false,"level":1,"children":[{"number":26,"description":"PUT http://77.102.250.113:17354/api/v1/books/7399","duration":0,"startTime":"2025-03-27T00:48:08.627682+05:30[Asia/Kolkata]","result":"SUCCESS","restQuery":{"method":"PUT","path":"http://77.102.250.113:17354/api/v1/books/7399","content":"{\n    \"id\": 7399,\n    \"name\": \"The Da Vinci Code by Dan Brown\",\n    \"author\": \"Dan Brown\",\n    \"publication\": \"Penguin Books\",\n    \"category\": \"Updated Category\",\n    \"pages\": \"500\",\n    \"price\": \"800\"\n}","contentType":"application/json","requestHeaders":"Accept\u003d*/*\n\t\t\t\tContent-Type\u003dapplication/json","requestCookies":"","responseHeaders":"Set-Cookie: JSESSIONID\u003d39CDAD17EF3D86407B582FE8904BC9FE; Path\u003d/; HttpOnly\nX-Content-Type-Options: nosniff\nX-XSS-Protection: 1; mode\u003dblock\nCache-Control: no-cache, no-store, max-age\u003d0, must-revalidate\nPragma: no-cache\nExpires: 0\nX-Frame-Options: DENY\nContent-Type: application/json\nTransfer-Encoding: chunked\nDate: Wed, 26 Mar 2025 19:18:07 GMT\nKeep-Alive: timeout\u003d60\nConnection: keep-alive","responseCookies":"JSESSIONID\u003d39CDAD17EF3D86407B582FE8904BC9FE;Path\u003d/;HttpOnly","responseBody":"{\n    \"id\": 7399,\n    \"name\": \"The Da Vinci Code by Dan Brown\",\n    \"author\": \"Dan Brown\",\n    \"publication\": \"Penguin Books\",\n    \"category\": \"Updated Category\",\n    \"pages\": 500,\n    \"price\": 800.0\n}","statusCode":200},"precondition":false,"level":2}]},{"number":27,"description":"Then The book details should be updated successfully","duration":1337,"startTime":"2025-03-27T00:48:08.633579+05:30[Asia/Kolkata]","result":"SUCCESS","precondition":false,"level":1,"children":[{"number":28,"description":"GET http://77.102.250.113:17354/api/v1/books/7399","duration":0,"startTime":"2025-03-27T00:48:09.965864+05:30[Asia/Kolkata]","result":"SUCCESS","restQuery":{"method":"GET","path":"http://77.102.250.113:17354/api/v1/books/7399","content":"","contentType":"null","requestHeaders":"Accept\u003d*/*","requestCookies":"","responseHeaders":"Set-Cookie: JSESSIONID\u003d9EA05F01F786D0556F2BCA08C9A5E4CE; Path\u003d/; HttpOnly\nX-Content-Type-Options: nosniff\nX-XSS-Protection: 1; mode\u003dblock\nCache-Control: no-cache, no-store, max-age\u003d0, must-revalidate\nPragma: no-cache\nExpires: 0\nX-Frame-Options: DENY\nContent-Type: application/json\nTransfer-Encoding: chunked\nDate: Wed, 26 Mar 2025 19:18:09 GMT\nKeep-Alive: timeout\u003d60\nConnection: keep-alive","responseCookies":"JSESSIONID\u003d9EA05F01F786D0556F2BCA08C9A5E4CE;Path\u003d/;HttpOnly","responseBody":"{\n    \"id\": 7399,\n    \"name\": \"The Da Vinci Code by Dan Brown\",\n    \"author\": \"Dan Brown\",\n    \"publication\": \"Penguin Books\",\n    \"category\": \"Updated Category\",\n    \"pages\": 500,\n    \"price\": 800.0\n}","statusCode":200},"precondition":false,"level":2}]}]},{"number":29,"description":"5: Successfully update a book\u0027s details ({TestCaseName\u003dUpdateBookDetails_PagesUpdate, FieldName\u003dpages})","duration":4174,"startTime":"2025-03-27T00:48:09.984050+05:30[Asia/Kolkata]","result":"FAILURE","precondition":false,"level":0,"lineNumber":80,"children":[{"number":30,"description":"Given A book already exists for test - \"UpdateBookDetails_PagesUpdate\"","duration":1449,"startTime":"2025-03-27T00:48:09.985433+05:30[Asia/Kolkata]","result":"SUCCESS","precondition":false,"level":1,"children":[{"number":31,"description":"POST http://77.102.250.113:17354/api/v1/books","duration":0,"startTime":"2025-03-27T00:48:11.419921+05:30[Asia/Kolkata]","result":"SUCCESS","restQuery":{"method":"POST","path":"http://77.102.250.113:17354/api/v1/books","content":"{\n    \"id\": 0,\n    \"name\": \"The Twilight Saga by Stephenie Meyer\",\n    \"author\": \"Stephenie Meyer\",\n    \"publication\": \"Scholastic\",\n    \"category\": \"Mobile\",\n    \"pages\": \"1000\",\n    \"price\": \"100\"\n}","contentType":"application/json","requestHeaders":"Accept\u003d*/*\n\t\t\t\tContent-Type\u003dapplication/json","requestCookies":"","responseHeaders":"Set-Cookie: JSESSIONID\u003d0299B39DED97BABBD672C8F1399C9C62; Path\u003d/; HttpOnly\nX-Content-Type-Options: nosniff\nX-XSS-Protection: 1; mode\u003dblock\nCache-Control: no-cache, no-store, max-age\u003d0, must-revalidate\nPragma: no-cache\nExpires: 0\nX-Frame-Options: DENY\nContent-Type: application/json\nTransfer-Encoding: chunked\nDate: Wed, 26 Mar 2025 19:18:10 GMT\nKeep-Alive: timeout\u003d60\nConnection: keep-alive","responseCookies":"JSESSIONID\u003d0299B39DED97BABBD672C8F1399C9C62;Path\u003d/;HttpOnly","responseBody":"{\n    \"id\": 7400,\n    \"name\": \"The Twilight Saga by Stephenie Meyer\",\n    \"author\": \"Stephenie Meyer\",\n    \"publication\": \"Scholastic\",\n    \"category\": \"Mobile\",\n    \"pages\": 1000,\n    \"price\": 100.0\n}","statusCode":200},"precondition":false,"level":2}]},{"number":32,"description":"When User updates the book details for field - \"pages\"","duration":1391,"startTime":"2025-03-27T00:48:11.436133+05:30[Asia/Kolkata]","result":"SUCCESS","precondition":false,"level":1,"children":[{"number":33,"description":"PUT http://77.102.250.113:17354/api/v1/books/7400","duration":0,"startTime":"2025-03-27T00:48:12.825632+05:30[Asia/Kolkata]","result":"SUCCESS","restQuery":{"method":"PUT","path":"http://77.102.250.113:17354/api/v1/books/7400","content":"{\n    \"id\": 7400,\n    \"name\": \"The Twilight Saga by Stephenie Meyer\",\n    \"author\": \"Stephenie Meyer\",\n    \"publication\": \"Scholastic\",\n    \"category\": \"Mobile\",\n    \"pages\": \"100\",\n    \"price\": \"100\"\n}","contentType":"application/json","requestHeaders":"Accept\u003d*/*\n\t\t\t\tContent-Type\u003dapplication/json","requestCookies":"","responseHeaders":"Set-Cookie: JSESSIONID\u003dD6E627A8973603FA8C5B290C184ED716; Path\u003d/; HttpOnly\nX-Content-Type-Options: nosniff\nX-XSS-Protection: 1; mode\u003dblock\nCache-Control: no-cache, no-store, max-age\u003d0, must-revalidate\nPragma: no-cache\nExpires: 0\nX-Frame-Options: DENY\nContent-Type: application/json\nTransfer-Encoding: chunked\nDate: Wed, 26 Mar 2025 19:18:12 GMT\nKeep-Alive: timeout\u003d60\nConnection: keep-alive","responseCookies":"JSESSIONID\u003dD6E627A8973603FA8C5B290C184ED716;Path\u003d/;HttpOnly","responseBody":"{\n    \"id\": 7400,\n    \"name\": \"The Twilight Saga by Stephenie Meyer\",\n    \"author\": \"Stephenie Meyer\",\n    \"publication\": \"Scholastic\",\n    \"category\": \"Mobile\",\n    \"pages\": 1000,\n    \"price\": 100.0\n}","statusCode":200},"precondition":false,"level":2}]},{"number":34,"description":"Then The book details should be updated successfully","duration":1326,"startTime":"2025-03-27T00:48:12.829074+05:30[Asia/Kolkata]","exception":{"errorType":"java.lang.AssertionError","message":"expected:\u003c100[]\u003e but was:\u003c100[0]\u003e","stackTrace":[{"declaringClass":"steps.BookApiSteps","methodName":"verifyBookDetails","fileName":"BookApiSteps.java","lineNumber":58},{"declaringClass":"stepDefinition.BookStepDefinitions","methodName":"theBookDetailsShouldBeUpdatedSuccessfully","fileName":"BookStepDefinitions.java","lineNumber":152},{"declaringClass":"✽","methodName":"The book details should be updated successfully","fileName":"file:///Users/bharathpalanisamy/Documents/BooksAPITestAutomation/src/test/resources/features/BooksAPIOperations.feature","lineNumber":72}]},"result":"FAILURE","precondition":false,"level":1,"children":[{"number":35,"description":"GET http://77.102.250.113:17354/api/v1/books/7400","duration":0,"startTime":"2025-03-27T00:48:14.141031+05:30[Asia/Kolkata]","result":"SUCCESS","restQuery":{"method":"GET","path":"http://77.102.250.113:17354/api/v1/books/7400","content":"","contentType":"null","requestHeaders":"Accept\u003d*/*","requestCookies":"","responseHeaders":"Set-Cookie: JSESSIONID\u003d88E1B9D9F1AD31F128270A5002B1D80C; Path\u003d/; HttpOnly\nX-Content-Type-Options: nosniff\nX-XSS-Protection: 1; mode\u003dblock\nCache-Control: no-cache, no-store, max-age\u003d0, must-revalidate\nPragma: no-cache\nExpires: 0\nX-Frame-Options: DENY\nContent-Type: application/json\nTransfer-Encoding: chunked\nDate: Wed, 26 Mar 2025 19:18:13 GMT\nKeep-Alive: timeout\u003d60\nConnection: keep-alive","responseCookies":"JSESSIONID\u003d88E1B9D9F1AD31F128270A5002B1D80C;Path\u003d/;HttpOnly","responseBody":"{\n    \"id\": 7400,\n    \"name\": \"The Twilight Saga by Stephenie Meyer\",\n    \"author\": \"Stephenie Meyer\",\n    \"publication\": \"Scholastic\",\n    \"category\": \"Mobile\",\n    \"pages\": 1000,\n    \"price\": 100.0\n}","statusCode":200},"precondition":false,"level":2}]}]},{"number":36,"description":"6: Successfully update a book\u0027s details ({TestCaseName\u003dUpdateBookDetails_PriceUpdate, FieldName\u003dprice})","duration":4292,"startTime":"2025-03-27T00:48:14.171406+05:30[Asia/Kolkata]","result":"SUCCESS","precondition":false,"level":0,"lineNumber":81,"children":[{"number":37,"description":"Given A book already exists for test - \"UpdateBookDetails_PriceUpdate\"","duration":1435,"startTime":"2025-03-27T00:48:14.171986+05:30[Asia/Kolkata]","result":"SUCCESS","precondition":false,"level":1,"children":[{"number":38,"description":"POST http://77.102.250.113:17354/api/v1/books","duration":0,"startTime":"2025-03-27T00:48:15.589860+05:30[Asia/Kolkata]","result":"SUCCESS","restQuery":{"method":"POST","path":"http://77.102.250.113:17354/api/v1/books","content":"{\n    \"id\": 0,\n    \"name\": \"Quotations from the Works of Mao Tse-Tung (Mao Zedong) \",\n    \"author\": \"Mao Tse-Tung\",\n    \"publication\": \"Penguin Random House\",\n    \"category\": \"History\",\n    \"pages\": \"234\",\n    \"price\": \"2220\"\n}","contentType":"application/json","requestHeaders":"Accept\u003d*/*\n\t\t\t\tContent-Type\u003dapplication/json","requestCookies":"","responseHeaders":"Set-Cookie: JSESSIONID\u003d452CBDD0838AA6EEF2F9C097078056E0; Path\u003d/; HttpOnly\nX-Content-Type-Options: nosniff\nX-XSS-Protection: 1; mode\u003dblock\nCache-Control: no-cache, no-store, max-age\u003d0, must-revalidate\nPragma: no-cache\nExpires: 0\nX-Frame-Options: DENY\nContent-Type: application/json\nTransfer-Encoding: chunked\nDate: Wed, 26 Mar 2025 19:18:14 GMT\nKeep-Alive: timeout\u003d60\nConnection: keep-alive","responseCookies":"JSESSIONID\u003d452CBDD0838AA6EEF2F9C097078056E0;Path\u003d/;HttpOnly","responseBody":"{\n    \"id\": 7401,\n    \"name\": \"Quotations from the Works of Mao Tse-Tung (Mao Zedong) \",\n    \"author\": \"Mao Tse-Tung\",\n    \"publication\": \"Penguin Random House\",\n    \"category\": \"History\",\n    \"pages\": 234,\n    \"price\": 2220.0\n}","statusCode":200},"precondition":false,"level":2}]},{"number":39,"description":"When User updates the book details for field - \"price\"","duration":1352,"startTime":"2025-03-27T00:48:15.608034+05:30[Asia/Kolkata]","result":"SUCCESS","precondition":false,"level":1,"children":[{"number":40,"description":"PUT http://77.102.250.113:17354/api/v1/books/7401","duration":0,"startTime":"2025-03-27T00:48:16.957519+05:30[Asia/Kolkata]","result":"SUCCESS","restQuery":{"method":"PUT","path":"http://77.102.250.113:17354/api/v1/books/7401","content":"{\n    \"id\": 7401,\n    \"name\": \"Quotations from the Works of Mao Tse-Tung (Mao Zedong) \",\n    \"author\": \"Mao Tse-Tung\",\n    \"publication\": \"Penguin Random House\",\n    \"category\": \"History\",\n    \"pages\": \"234\",\n    \"price\": \"2090\"\n}","contentType":"application/json","requestHeaders":"Accept\u003d*/*\n\t\t\t\tContent-Type\u003dapplication/json","requestCookies":"","responseHeaders":"Set-Cookie: JSESSIONID\u003d546ABD1DF5D1C90A585D9953AE0AC42E; Path\u003d/; HttpOnly\nX-Content-Type-Options: nosniff\nX-XSS-Protection: 1; mode\u003dblock\nCache-Control: no-cache, no-store, max-age\u003d0, must-revalidate\nPragma: no-cache\nExpires: 0\nX-Frame-Options: DENY\nContent-Type: application/json\nTransfer-Encoding: chunked\nDate: Wed, 26 Mar 2025 19:18:16 GMT\nKeep-Alive: timeout\u003d60\nConnection: keep-alive","responseCookies":"JSESSIONID\u003d546ABD1DF5D1C90A585D9953AE0AC42E;Path\u003d/;HttpOnly","responseBody":"{\n    \"id\": 7401,\n    \"name\": \"Quotations from the Works of Mao Tse-Tung (Mao Zedong) \",\n    \"author\": \"Mao Tse-Tung\",\n    \"publication\": \"Penguin Random House\",\n    \"category\": \"History\",\n    \"pages\": 234,\n    \"price\": 2090.0\n}","statusCode":200},"precondition":false,"level":2}]},{"number":41,"description":"Then The book details should be updated successfully","duration":1500,"startTime":"2025-03-27T00:48:16.961977+05:30[Asia/Kolkata]","result":"SUCCESS","precondition":false,"level":1,"children":[{"number":42,"description":"GET http://77.102.250.113:17354/api/v1/books/7401","duration":0,"startTime":"2025-03-27T00:48:18.456392+05:30[Asia/Kolkata]","result":"SUCCESS","restQuery":{"method":"GET","path":"http://77.102.250.113:17354/api/v1/books/7401","content":"","contentType":"null","requestHeaders":"Accept\u003d*/*","requestCookies":"","responseHeaders":"Set-Cookie: JSESSIONID\u003d6DB5A26B5C7FA8BF89771A72CD9E750C; Path\u003d/; HttpOnly\nX-Content-Type-Options: nosniff\nX-XSS-Protection: 1; mode\u003dblock\nCache-Control: no-cache, no-store, max-age\u003d0, must-revalidate\nPragma: no-cache\nExpires: 0\nX-Frame-Options: DENY\nContent-Type: application/json\nTransfer-Encoding: chunked\nDate: Wed, 26 Mar 2025 19:18:17 GMT\nKeep-Alive: timeout\u003d60\nConnection: keep-alive","responseCookies":"JSESSIONID\u003d6DB5A26B5C7FA8BF89771A72CD9E750C;Path\u003d/;HttpOnly","responseBody":"{\n    \"id\": 7401,\n    \"name\": \"Quotations from the Works of Mao Tse-Tung (Mao Zedong) \",\n    \"author\": \"Mao Tse-Tung\",\n    \"publication\": \"Penguin Random House\",\n    \"category\": \"History\",\n    \"pages\": 234,\n    \"price\": 2090.0\n}","statusCode":200},"precondition":false,"level":2}]}]},{"number":43,"description":"7: Successfully update a book\u0027s details ({TestCaseName\u003dUpdateBookDetails_MultipleFieldsUpdate, FieldName\u003dMultipleFields})","duration":4054,"startTime":"2025-03-27T00:48:18.481139+05:30[Asia/Kolkata]","result":"FAILURE","precondition":false,"level":0,"lineNumber":82,"children":[{"number":44,"description":"Given A book already exists for test - \"UpdateBookDetails_MultipleFieldsUpdate\"","duration":1362,"startTime":"2025-03-27T00:48:18.482038+05:30[Asia/Kolkata]","result":"SUCCESS","precondition":false,"level":1,"children":[{"number":45,"description":"POST http://77.102.250.113:17354/api/v1/books","duration":0,"startTime":"2025-03-27T00:48:19.825431+05:30[Asia/Kolkata]","result":"SUCCESS","restQuery":{"method":"POST","path":"http://77.102.250.113:17354/api/v1/books","content":"{\n    \"id\": 0,\n    \"name\": \"The Room on the Roof by Ruskin Bond \",\n    \"author\": \"Ruskin Bond\",\n    \"publication\": \"Simon \u0026 Schuster\",\n    \"category\": \"Science\",\n    \"pages\": \"2300\",\n    \"price\": \"3440\"\n}","contentType":"application/json","requestHeaders":"Accept\u003d*/*\n\t\t\t\tContent-Type\u003dapplication/json","requestCookies":"","responseHeaders":"Set-Cookie: JSESSIONID\u003d3B53784BCC04B36CB2CD82757D50B37E; Path\u003d/; HttpOnly\nX-Content-Type-Options: nosniff\nX-XSS-Protection: 1; mode\u003dblock\nCache-Control: no-cache, no-store, max-age\u003d0, must-revalidate\nPragma: no-cache\nExpires: 0\nX-Frame-Options: DENY\nContent-Type: application/json\nTransfer-Encoding: chunked\nDate: Wed, 26 Mar 2025 19:18:18 GMT\nKeep-Alive: timeout\u003d60\nConnection: keep-alive","responseCookies":"JSESSIONID\u003d3B53784BCC04B36CB2CD82757D50B37E;Path\u003d/;HttpOnly","responseBody":"{\n    \"id\": 7402,\n    \"name\": \"The Room on the Roof by Ruskin Bond \",\n    \"author\": \"Ruskin Bond\",\n    \"publication\": \"Simon \u0026 Schuster\",\n    \"category\": \"Science\",\n    \"pages\": 2300,\n    \"price\": 3440.0000001\n}","statusCode":200},"precondition":false,"level":2}]},{"number":46,"description":"When User updates the book details for field - \"MultipleFields\"","duration":1306,"startTime":"2025-03-27T00:48:19.845551+05:30[Asia/Kolkata]","result":"SUCCESS","precondition":false,"level":1,"children":[{"number":47,"description":"PUT http://77.102.250.113:17354/api/v1/books/7402","duration":0,"startTime":"2025-03-27T00:48:21.149311+05:30[Asia/Kolkata]","result":"SUCCESS","restQuery":{"method":"PUT","path":"http://77.102.250.113:17354/api/v1/books/7402","content":"{\n    \"id\": 7402,\n    \"name\": \"Updated Name\",\n    \"author\": \"Updated Author\",\n    \"publication\": \"Updated Publication\",\n    \"category\": \"Updated Category\",\n    \"pages\": \"100\",\n    \"price\": \"2090\"\n}","contentType":"application/json","requestHeaders":"Accept\u003d*/*\n\t\t\t\tContent-Type\u003dapplication/json","requestCookies":"","responseHeaders":"Set-Cookie: JSESSIONID\u003d56AE5D1B73B65019ED4E3BBA60B667FE; Path\u003d/; HttpOnly\nX-Content-Type-Options: nosniff\nX-XSS-Protection: 1; mode\u003dblock\nCache-Control: no-cache, no-store, max-age\u003d0, must-revalidate\nPragma: no-cache\nExpires: 0\nX-Frame-Options: DENY\nContent-Type: application/json\nTransfer-Encoding: chunked\nDate: Wed, 26 Mar 2025 19:18:20 GMT\nKeep-Alive: timeout\u003d60\nConnection: keep-alive","responseCookies":"JSESSIONID\u003d56AE5D1B73B65019ED4E3BBA60B667FE;Path\u003d/;HttpOnly","responseBody":"{\n    \"id\": 7402,\n    \"name\": \"Updated Name\",\n    \"author\": \"Updated Author\",\n    \"publication\": \"Updated Publication\",\n    \"category\": \"Updated Category\",\n    \"pages\": 2300,\n    \"price\": 2090.0\n}","statusCode":200},"precondition":false,"level":2}]},{"number":48,"description":"Then The book details should be updated successfully","duration":1380,"startTime":"2025-03-27T00:48:21.153373+05:30[Asia/Kolkata]","exception":{"errorType":"java.lang.AssertionError","message":"expected:\u003c[1]00\u003e but was:\u003c[23]00\u003e","stackTrace":[{"declaringClass":"steps.BookApiSteps","methodName":"verifyBookDetails","fileName":"BookApiSteps.java","lineNumber":58},{"declaringClass":"stepDefinition.BookStepDefinitions","methodName":"theBookDetailsShouldBeUpdatedSuccessfully","fileName":"BookStepDefinitions.java","lineNumber":152},{"declaringClass":"✽","methodName":"The book details should be updated successfully","fileName":"file:///Users/bharathpalanisamy/Documents/BooksAPITestAutomation/src/test/resources/features/BooksAPIOperations.feature","lineNumber":72}]},"result":"FAILURE","precondition":false,"level":1,"children":[{"number":49,"description":"GET http://77.102.250.113:17354/api/v1/books/7402","duration":0,"startTime":"2025-03-27T00:48:22.521822+05:30[Asia/Kolkata]","result":"SUCCESS","restQuery":{"method":"GET","path":"http://77.102.250.113:17354/api/v1/books/7402","content":"","contentType":"null","requestHeaders":"Accept\u003d*/*","requestCookies":"","responseHeaders":"Set-Cookie: JSESSIONID\u003d2E42968933CDD16C36C9F4BD57AFC73D; Path\u003d/; HttpOnly\nX-Content-Type-Options: nosniff\nX-XSS-Protection: 1; mode\u003dblock\nCache-Control: no-cache, no-store, max-age\u003d0, must-revalidate\nPragma: no-cache\nExpires: 0\nX-Frame-Options: DENY\nContent-Type: application/json\nTransfer-Encoding: chunked\nDate: Wed, 26 Mar 2025 19:18:21 GMT\nKeep-Alive: timeout\u003d60\nConnection: keep-alive","responseCookies":"JSESSIONID\u003d2E42968933CDD16C36C9F4BD57AFC73D;Path\u003d/;HttpOnly","responseBody":"{\n    \"id\": 7402,\n    \"name\": \"Updated Name\",\n    \"author\": \"Updated Author\",\n    \"publication\": \"Updated Publication\",\n    \"category\": \"Updated Category\",\n    \"pages\": 2300,\n    \"price\": 2090.0\n}","statusCode":200},"precondition":false,"level":2}]}]}],"userStory":{"id":"BooksAPIOperations","storyName":"Books API CRUD operations","displayName":"Books API CRUD operations","path":"BooksAPIOperations","pathElements":[{"name":"BooksAPIOperations","description":""}],"type":"feature"},"title":"Successfully update a book\u0027s details","description":"","startTime":"2025-03-27T00:47:53.175823+05:30[Asia/Kolkata]","endTime":"2025-03-27T00:48:22.521970+05:30[Asia/Kolkata]","duration":1339,"testFailureCause":{"errorType":"net.thucydides.model.domain.MultipleAssertionErrors","message":"\nThe following 3 assertions failed:\n1) expected:\u003c100[]\u003e but was:\u003c100[0]\u003e\n2) expected:\u003c[1]00\u003e but was:\u003c[23]00\u003e\n3) expected:\u003c[1]00\u003e but was:\u003c[23]00\u003e\n","stackTrace":[]},"testFailureClassname":"net.thucydides.model.domain.MultipleAssertionErrors","testFailureMessage":"\nThe following 3 assertions failed:\n1) expected:\u003c100[]\u003e but was:\u003c100[0]\u003e\n2) expected:\u003c[1]00\u003e but was:\u003c[23]00\u003e\n3) expected:\u003c[1]00\u003e but was:\u003c[23]00\u003e\n","testFailureSummary":"\nThe following 3 assertions failed:\n1) expected:\u003c100[]\u003e but was:\u003c100[0]\u003e\n2) expected:\u003c[1]00\u003e but was:\u003c[23]00\u003e\n3) expected:\u003c[1]00\u003e but was:\u003c[23]00\u003e\n","projectKey":"","annotatedResult":"FAILURE","isManualTestingUpToDate":false,"dataTable":{"headers":["TestCaseName","FieldName"],"rows":[{"values":["UpdateBookDetails_NameUpdate","name"],"lineNumber":76,"result":"SUCCESS"},{"values":["UpdateBookDetails_AuthorUpdate","author"],"lineNumber":77,"result":"SUCCESS"},{"values":["UpdateBookDetails_PublicationUpdate","publication"],"lineNumber":78,"result":"SUCCESS"},{"values":["UpdateBookDetails_CategoryUpdate","category"],"lineNumber":79,"result":"SUCCESS"},{"values":["UpdateBookDetails_PagesUpdate","pages"],"lineNumber":80,"result":"FAILURE"},{"values":["UpdateBookDetails_PriceUpdate","price"],"lineNumber":81,"result":"SUCCESS"},{"values":["UpdateBookDetails_MultipleFieldsUpdate","MultipleFields"],"lineNumber":82,"result":"FAILURE"}],"predefinedRows":true,"scenarioOutline":"Given A book already exists for test - \"\u003cTestCaseName\u003e\"\n\rWhen User updates the book details for field - \"\u003cFieldName\u003e\"\n\rThen The book details should be updated successfully\n\r","dataSetDescriptors":[{"startRow":0,"rowCount":0,"name":"","description":""}]},"manual":false,"testSource":"Cucumber","order":0,"result":"FAILURE","scenarioOutline":"Given A book already exists for test - \"\u003cTestCaseName\u003e\"\nWhen User updates the book details for field - \"\u003cFieldName\u003e\"\nThen The book details should be updated successfully"}